{
  "main": {
    "id": "f0777b2c31d8ec30",
    "type": "split",
    "children": [
      {
        "id": "6babeb96ebe278a5",
        "type": "tabs",
        "children": [
          {
            "id": "46133dad091ad21b",
            "type": "leaf",
            "state": {
              "type": "markdown",
              "state": {
                "file": "0. INBOX/1.2 문헌 검토.md",
                "mode": "source",
                "source": false,
                "backlinks": true,
                "backlinkOpts": {
                  "collapseAll": false,
                  "extraContext": false,
                  "sortOrder": "alphabetical",
                  "showSearch": false,
                  "searchQuery": "",
                  "backlinkCollapsed": false,
                  "unlinkedCollapsed": true
                }
              },
              "icon": "lucide-file",
              "title": "1.2 문헌 검토"
            }
          }
        ]
      }
    ],
    "direction": "vertical"
  },
  "left": {
    "id": "b3cce1328d470616",
    "type": "split",
    "children": [
      {
        "id": "a83c5c6d64203767",
        "type": "tabs",
        "dimension": 52.333664349553125,
        "children": [
          {
            "id": "84301899b043e26d",
            "type": "leaf",
            "state": {
              "type": "file-explorer",
              "state": {
                "sortOrder": "alphabetical",
                "autoReveal": false
              },
              "icon": "lucide-folder-closed",
              "title": "파일 탐색기"
            }
          },
          {
            "id": "fc4869faacd2a1f0",
            "type": "leaf",
            "state": {
              "type": "search",
              "state": {
                "query": "리뷰_2023",
                "matchingCase": false,
                "explainSearch": false,
                "collapseAll": false,
                "extraContext": false,
                "sortOrder": "alphabetical"
              },
              "icon": "lucide-search",
              "title": "검색"
            }
          },
          {
            "id": "49003568af04693e",
            "type": "leaf",
            "state": {
              "type": "bookmarks",
              "state": {},
              "icon": "lucide-bookmark",
              "title": "북마크"
            }
          }
        ],
        "currentTab": 1
      },
      {
        "id": "f688897bf0516395",
        "type": "tabs",
        "dimension": 27.805362462760673,
        "children": [
          {
            "id": "1b052f6f0fe0224e",
            "type": "leaf",
            "state": {
              "type": "tag",
              "state": {
                "sortOrder": "frequency",
                "useHierarchy": true,
                "showSearch": false,
                "searchQuery": ""
              },
              "icon": "lucide-tags",
              "title": "태그"
            }
          },
          {
            "id": "547a2eb80fe9737e",
            "type": "leaf",
            "state": {
              "type": "all-properties",
              "state": {
                "sortOrder": "frequency",
                "showSearch": false,
                "searchQuery": ""
              },
              "icon": "lucide-archive",
              "title": "모든 속성"
            }
          },
          {
            "id": "0e60e462f894a333",
            "type": "leaf",
            "state": {
              "type": "graph",
              "state": {},
              "icon": "lucide-git-fork",
              "title": "그래프 뷰"
            }
          }
        ],
        "currentTab": 2
      },
      {
        "id": "eac9abe5fe92f719",
        "type": "tabs",
        "dimension": 19.860973187686195,
        "children": [
          {
            "id": "377b20c0487fff01",
            "type": "leaf",
            "state": {
              "type": "git-view",
              "state": {},
              "icon": "git-pull-request",
              "title": "Source Control"
            }
          },
          {
            "id": "1dc4a50d117cffe1",
            "type": "leaf",
            "state": {
              "type": "backlink",
              "state": {
                "file": "7. OUTPUTS/MOC_졸업논문 목차.md",
                "collapseAll": false,
                "extraContext": false,
                "sortOrder": "alphabetical",
                "showSearch": false,
                "searchQuery": "",
                "backlinkCollapsed": false,
                "unlinkedCollapsed": false
              },
              "icon": "links-coming-in",
              "title": "MOC_졸업논문 목차 의 백링크"
            }
          },
          {
            "id": "f9137678fa1352ca",
            "type": "leaf",
            "state": {
              "type": "outgoing-link",
              "state": {
                "file": "7. OUTPUTS/MOC_졸업논문 목차.md",
                "linksCollapsed": false,
                "unlinkedCollapsed": true
              },
              "icon": "links-going-out",
              "title": "MOC_졸업논문 목차 의 나가는 링크"
            }
          }
        ]
      }
    ],
    "direction": "horizontal",
    "width": 293.5
  },
  "right": {
    "id": "f6e3a5d123567eda",
    "type": "split",
    "children": [
      {
        "id": "30fb6174ca5a12b2",
        "type": "tabs",
        "children": [
          {
            "id": "e0f02b6e118fd73b",
            "type": "leaf",
            "state": {
              "type": "outline",
              "state": {
                "file": "7. OUTPUTS/MOC_졸업논문 목차.md",
                "followCursor": false,
                "showSearch": false,
                "searchQuery": ""
              },
              "icon": "lucide-list",
              "title": "MOC_졸업논문 목차 의 개요"
            }
          },
          {
            "id": "952b8bf6a5dc24a8",
            "type": "leaf",
            "state": {
              "type": "github-copilot-chat-view",
              "state": {},
              "icon": "bot-message-square",
              "title": "Copilot Chat"
            }
          }
        ],
        "currentTab": 1
      }
    ],
    "direction": "horizontal",
    "width": 376.5
  },
  "left-ribbon": {
    "hiddenItems": {
      "switcher:빠른 전환기 열기": false,
      "graph:그래프 뷰 열기": false,
      "canvas:새 캔버스 만들기": false,
      "daily-notes:오늘의 일일 노트 열기": false,
      "templates:템플릿 삽입": false,
      "command-palette:명령어 팔레트 열기": false,
      "obsidian-git:Open Git source control": false,
      "templater-obsidian:Templater": false,
      "audio-recorder:녹음 시작/정지": false,
      "workspaces:작업 공간 레이아웃 관리": false,
      "publish:변경사항 게재": false
    }
  },
  "active": "0e60e462f894a333",
  "lastOpenFiles": [
    "97. TEMPLATES/Temp_MOC.md",
    "0. INBOX/1.2 문헌 검토.md",
    "7. OUTPUTS/MOC_졸업논문.md",
    "0. INBOX/1.1 연구 배경.md",
    "3. CONCEPTS/대형 선박의 저인화점 연료 사용.md",
    "2. REVIEWS/리뷰_Liquefied Natural Gas (LNG) Import Terminals Siting, Safety, and Regulation.md",
    "2. REVIEWS/리뷰_저인화점연료 추진선박기준.md",
    "3. CONCEPTS/저인화점 연료.md",
    "7. OUTPUTS/MOC_수소선박 IMO CCC회의 동향 및 규제 검토.md",
    "0. INBOX/기관실 화재 사고 데이터베이스.md",
    "3. CONCEPTS/액체수소의 기술적·산업적 필요성.md",
    "0. INBOX/수소에너지의 수요증가.md",
    "3. CONCEPTS/자연 발화 CFD 시뮬레이션 주요 출력 내용.md",
    "3. CONCEPTS/메탄올 (Methanol).md",
    "3. CONCEPTS/액체수소 선박 기술.md",
    "3. CONCEPTS/액화천연가스 (LNG).md",
    "3. CONCEPTS/저인화점 연료 누출·자연발화 관련 연구.md",
    "3. CONCEPTS/저인화점 연료 증가와 화재 위험성.md",
    "3. CONCEPTS/해운업의 탈탄소화와 대체 연료 도입.md",
    "3. CONCEPTS/CFD 기반 자연발화 위험 예측의 필요성.md",
    "3. CONCEPTS/CFD 기반 화재 시뮬레이션 연구 동향.md",
    "0. INBOX/IGF Code.md",
    "2. REVIEWS/IMO CCC의 회의 동향 및 지침 검토.md",
    "3. CONCEPTS/IMO의 탈탄소화 규제 동향.md",
    "3. CONCEPTS/수소 (Hydrogen).md",
    "3. CONCEPTS/암모니아 (Ammonia).md",
    "발화온도, LEL",
    "98. RESOURCES/저인화점연료 추진선박기준(해양수산부고시)(제2020-94호)(20200708).pdf",
    "0. INBOX",
    "99. ATTACHMENTS/Pasted image 20250718143043.png",
    "99. ATTACHMENTS/Pasted image 20250718143027.png",
    "99. ATTACHMENTS/Pasted image 20250718143005.png",
    "99. ATTACHMENTS/Pasted image 20250718142945.png",
    "98. RESOURCES/Science and technology of ammonia combustion.pdf",
    "98. RESOURCES/PRS_SAFETY REQUIREMENTS FOR SHIPS USING LOW-FLASHPOINT GASES AS FUEL.pdf",
    "98. RESOURCES/Liquefied Natural Gas (LNG) Import Terminals Siting, Safety, and Regulation.pdf",
    "98. RESOURCES/KR_저인화점연료선박에 대한 지침서(LPG & 메틸에틸 알코올)(국).pdf",
    "98. RESOURCES/KR_암모니아 연료선박에 대한 지침서.pdf",
    "98. RESOURCES/KR_무탄소 선박연료로서 암모니아의 전망.pdf",
    "98. RESOURCES/HYDROGEN ON BOARD SHIP A FIRST ANALYSIS OF KEY PARAMETERS AND IMPLICATIONS.pdf",
    "NODE/node_modules/npm/node_modules/qrcode-terminal/example/basic.png",
    "NODE/node_modules/npm/node_modules/retry/equation.gif",
    "node_modules/npm/node_modules/retry/equation.gif",
    "node_modules/npm/node_modules/qrcode-terminal/example/basic.png",
    "Pasted image 20250718143043.png",
    "Pasted image 20250718143027.png",
    "무제.canvas"
  ]
}